Metadata-Version: 2.1
Name: dy-menu
Version: 1.0.0
Summary: A light weight command line menu that supports Windows, MacOS, and Linux
Author: clever chen
Author-email: 
Keywords: python,menu,dumb_menu,windows,mac,linux
Classifier: Development Status :: 1 - Planning
Classifier: Intended Audience :: Developers
Classifier: Programming Language :: Python :: 3
Classifier: Operating System :: Unix
Classifier: Operating System :: MacOS :: MacOS X
Classifier: Operating System :: Microsoft :: Windows
